{
  "sailnumber": "TUR/TUR2306",
  "country": "TUR",
  "name": "C FOR SEA",
  "rating": {
    "gph": 592.5,
    "osn": 574.4,
    "triple_offshore": [
      0.8942,
      1.1386,
      1.2707
    ],
    "triple_inshore": [
      0.6984,
      0.9326,
      1.0515
    ]
  },
  "boat": {
    "builder": "Arhambault",
    "type": "A-35",
    "designer": "Nivelt",
    "year": 2005,
    "sizes": {
      "loa": 10.617,
      "beam": 3.59,
      "draft": 2.16,
      "displacement": 4495.0,
      "genoa": 29.3,
      "main": 38.16,
      "spinnaker": 0.0,
      "spinnaker_asym": 120.51,
      "crew": 700.0,
      "wetted_surface": 24.83
    },
    "stability_index": -1.0
  },
  "vpp": {
    "angles": [
      52,
      60,
      75,
      90,
      110,
      120,
      135,
      150
    ],
    "speeds": [
      4,
      6,
      8,
      10,
      12,
      14,
      16,
      20,
      24
    ],
    "52": [
      4.05,
      5.47,
      6.47,
      7.05,
      7.33,
      7.47,
      7.56,
      7.65,
      7.68
    ],
    "60": [
      4.3,
      5.74,
      6.69,
      7.2,
      7.5,
      7.68,
      7.78,
      7.9,
      7.95
    ],
    "75": [
      4.45,
      5.89,
      6.81,
      7.31,
      7.64,
      7.92,
      8.12,
      8.34,
      8.46
    ],
    "90": [
      4.49,
      6.03,
      7.06,
      7.49,
      7.73,
      7.96,
      8.26,
      8.75,
      9.05
    ],
    "110": [
      4.61,
      6.18,
      7.24,
      7.8,
      8.25,
      8.55,
      8.83,
      9.35,
      9.86
    ],
    "120": [
      4.47,
      6.05,
      7.15,
      7.75,
      8.26,
      8.77,
      9.24,
      9.99,
      10.82
    ],
    "135": [
      3.89,
      5.45,
      6.68,
      7.41,
      7.93,
      8.46,
      9.04,
      10.78,
      13.15
    ],
    "150": [
      3.24,
      4.59,
      5.76,
      6.73,
      7.38,
      7.82,
      8.26,
      9.27,
      12.27
    ],
    "beat_angle": [
      42.3,
      42.3,
      40.3,
      38.5,
      37.4,
      36.7,
      36.4,
      36.3,
      37.3
    ],
    "beat_vmg": [
      2.62,
      3.62,
      4.42,
      4.98,
      5.27,
      5.41,
      5.49,
      5.57,
      5.53
    ],
    "run_angle": [
      143,
      143,
      147.1,
      150.1,
      153.3,
      157.2,
      159.5,
      145.6,
      142.8
    ],
    "run_vmg": [
      2.81,
      3.98,
      4.99,
      5.83,
      6.43,
      6.85,
      7.23,
      8.02,
      10.62
    ]
  }
}