{
  "sailnumber": "NED/NED8990",
  "country": "NED",
  "name": "Xiu",
  "owner": "-",
  "rating": {
    "gph": 605.1,
    "osn": 588.6,
    "triple_offshore": [
      0.9691,
      1.2623,
      1.4141
    ],
    "triple_inshore": [
      0.7458,
      1.0172,
      1.1755
    ]
  },
  "boat": {
    "builder": "X-Yachts",
    "type": "X-40",
    "designer": "N. Jepessen",
    "year": 2004,
    "sizes": {
      "loa": 12.225,
      "beam": 3.76,
      "draft": 2.09,
      "displacement": 7720.0,
      "genoa": 35.76,
      "main": 50.65,
      "spinnaker": 0.0,
      "spinnaker_asym": 97.72,
      "crew": 488.0,
      "wetted_surface": 32.16
    }
  },
  "vpp": {
    "angles": [
      52,
      60,
      75,
      90,
      110,
      120,
      135,
      150
    ],
    "speeds": [
      6,
      8,
      10,
      12,
      14,
      16,
      20
    ],
    "52": [
      5.36,
      6.38,
      7.1,
      7.44,
      7.58,
      7.63,
      7.7
    ],
    "60": [
      5.68,
      6.71,
      7.35,
      7.65,
      7.81,
      7.87,
      7.91
    ],
    "75": [
      5.96,
      6.97,
      7.53,
      7.84,
      8.06,
      8.22,
      8.37
    ],
    "90": [
      5.91,
      7.08,
      7.68,
      7.92,
      8.15,
      8.41,
      8.86
    ],
    "110": [
      5.92,
      7.14,
      7.77,
      8.16,
      8.53,
      8.78,
      9.19
    ],
    "120": [
      5.74,
      6.95,
      7.66,
      8.08,
      8.49,
      8.92,
      9.58
    ],
    "135": [
      5.13,
      6.3,
      7.23,
      7.76,
      8.15,
      8.57,
      9.53
    ],
    "150": [
      4.29,
      5.41,
      6.4,
      7.23,
      7.74,
      8.11,
      8.93
    ],
    "beat_angle": [
      43.2,
      41.6,
      41.2,
      40.6,
      40,
      39.9,
      39.7
    ],
    "beat_vmg": [
      3.49,
      4.23,
      4.79,
      5.12,
      5.24,
      5.29,
      5.37
    ],
    "run_angle": [
      144,
      149.2,
      151.3,
      155.3,
      170,
      180,
      180
    ],
    "run_vmg": [
      3.71,
      4.68,
      5.54,
      6.32,
      6.98,
      7.55,
      8.3
    ]
  }
}