{
  "sailnumber": "AUS/SP97",
  "country": "AUS",
  "name": "Mistress Quickly",
  "rating": {
    "gph": 649.0,
    "osn": 629.1,
    "triple_offshore": [
      0.7994,
      1.0471,
      1.1837
    ],
    "triple_inshore": [
      0.6136,
      0.8498,
      0.9785
    ]
  },
  "boat": {
    "builder": "Swarbrick",
    "type": "Swarbrick 9.7",
    "designer": "Swarbrick",
    "year": 2000,
    "sizes": {
      "loa": 9.6,
      "beam": 3.3,
      "draft": 1.7,
      "displacement": 3082.0,
      "genoa": 24.21,
      "main": 33.03,
      "spinnaker": 60.79,
      "spinnaker_asym": 0.0,
      "crew": 557.0,
      "wetted_surface": 20.52
    },
    "stability_index": 106.8
  },
  "vpp": {
    "angles": [
      52,
      60,
      75,
      90,
      110,
      120,
      135,
      150
    ],
    "speeds": [
      6,
      8,
      10,
      12,
      14,
      16,
      20
    ],
    "52": [
      5.02,
      6.0,
      6.6,
      6.88,
      6.98,
      7.04,
      7.06
    ],
    "60": [
      5.35,
      6.29,
      6.78,
      7.05,
      7.2,
      7.28,
      7.33
    ],
    "75": [
      5.6,
      6.51,
      6.93,
      7.24,
      7.53,
      7.73,
      7.89
    ],
    "90": [
      5.54,
      6.52,
      7.04,
      7.38,
      7.65,
      8.02,
      8.51
    ],
    "110": [
      5.47,
      6.57,
      7.12,
      7.6,
      8.12,
      8.55,
      9.11
    ],
    "120": [
      5.29,
      6.41,
      7.02,
      7.5,
      8.03,
      8.61,
      9.76
    ],
    "135": [
      4.74,
      5.84,
      6.69,
      7.16,
      7.63,
      8.16,
      9.48
    ],
    "150": [
      3.91,
      4.98,
      5.97,
      6.74,
      7.17,
      7.61,
      8.63
    ],
    "beat_angle": [
      43.8,
      42.3,
      41.2,
      39.3,
      39,
      38.8,
      39.6
    ],
    "beat_vmg": [
      3.26,
      3.96,
      4.51,
      4.84,
      4.95,
      4.99,
      4.97
    ],
    "run_angle": [
      145.1,
      150.2,
      149.8,
      157.9,
      173,
      179,
      177.2
    ],
    "run_vmg": [
      3.39,
      4.32,
      5.17,
      5.96,
      6.55,
      7.01,
      7.84
    ]
  }
}