{
  "rating": {
    "triple_offshore": [
      0.9002, 
      1.179, 
      1.3357
    ], 
    "triple_inshore": [
      0.6914, 
      0.9396, 
      1.0988
    ], 
    "gph": 648.0, 
    "osn": 630.0
  }, 
  "sailnumber": "NOR/NOR14206", 
  "name": "El Torres", 
  "country": "NOR", 
  "owner": "-", 
  "boat": {
    "builder": "Hanse Yachtbau", 
    "designer": "Judel/Vrolijk", 
    "type": "Hanse 350", 
    "sizes": {
      "beam": 3.55, 
      "spinnaker": 0.0, 
      "loa": 10.55, 
      "draft": 1.87, 
      "wetted_surface": 28.49, 
      "main": 36.05, 
      "genoa": 39.08, 
      "displacement": 6338.0, 
      "spinnaker_asym": 90.03, 
      "crew": 673.0
    }, 
    "year": 2008
  }, 
  "vpp": {
    "beat_vmg": [
      3.19, 
      3.85, 
      4.35, 
      4.77, 
      4.99, 
      5.11, 
      5.19
    ], 
    "150": [
      4.05, 
      5.11, 
      6.0, 
      6.71, 
      7.12, 
      7.44, 
      7.97
    ], 
    "135": [
      4.77, 
      5.87, 
      6.79, 
      7.31, 
      7.66, 
      8.02, 
      8.84
    ], 
    "75": [
      5.61, 
      6.62, 
      7.15, 
      7.45, 
      7.7, 
      7.92, 
      8.18
    ], 
    "run_angle": [
      145.6, 
      147.8, 
      147.4, 
      148.4, 
      151.7, 
      176.1, 
      178.3
    ], 
    "110": [
      5.46, 
      6.63, 
      7.28, 
      7.65, 
      8.04, 
      8.45, 
      8.88
    ], 
    "52": [
      4.95, 
      5.9, 
      6.63, 
      7.05, 
      7.26, 
      7.35, 
      7.43
    ], 
    "beat_angle": [
      44.5, 
      43.1, 
      43.2, 
      42.4, 
      40.9, 
      40.6, 
      40.3
    ], 
    "angles": [
      52, 
      60, 
      75, 
      90, 
      110, 
      120, 
      135, 
      150
    ], 
    "120": [
      5.29, 
      6.44, 
      7.17, 
      7.56, 
      7.93, 
      8.35, 
      9.26
    ], 
    "90": [
      5.61, 
      6.62, 
      7.23, 
      7.6, 
      7.78, 
      8.0, 
      8.53
    ], 
    "60": [
      5.29, 
      6.28, 
      6.93, 
      7.27, 
      7.48, 
      7.59, 
      7.68
    ], 
    "speeds": [
      6, 
      8, 
      10, 
      12, 
      14, 
      16, 
      20
    ], 
    "run_vmg": [
      3.51, 
      4.42, 
      5.19, 
      5.81, 
      6.2, 
      6.79, 
      7.5
    ]
  }
}