{
  "sailnumber": "NOR/NOR12383",
  "country": "NOR",
  "name": "JYSLA L\u00d8YE",
  "rating": {
    "gph": 527.5,
    "osn": 514.1,
    "triple_offshore": [
      1.1479,
      1.4263,
      1.6074
    ],
    "triple_inshore": [
      0.8955,
      1.1622,
      1.328
    ]
  },
  "boat": {
    "builder": "Carrol Marine",
    "type": "FARR 40 OD",
    "designer": "Farr",
    "year": 1996,
    "sizes": {
      "loa": 12.41,
      "beam": 3.96,
      "draft": 2.59,
      "displacement": 4989.0,
      "genoa": 40.7,
      "main": 64.72,
      "spinnaker": 161.88,
      "spinnaker_asym": 0.0,
      "crew": 777.0,
      "wetted_surface": 29.8
    }
  },
  "vpp": {
    "angles": [
      52,
      60,
      75,
      90,
      110,
      120,
      135,
      150
    ],
    "speeds": [
      6,
      8,
      10,
      12,
      14,
      16,
      20
    ],
    "52": [
      6.43,
      7.51,
      7.85,
      7.99,
      8.07,
      8.19,
      8.32
    ],
    "60": [
      6.81,
      7.74,
      8.08,
      8.25,
      8.37,
      8.47,
      8.71
    ],
    "75": [
      7.1,
      7.91,
      8.36,
      8.71,
      8.92,
      9.06,
      9.38
    ],
    "90": [
      7.03,
      7.89,
      8.42,
      8.96,
      9.41,
      9.71,
      10.05
    ],
    "110": [
      6.86,
      7.96,
      8.49,
      8.93,
      9.37,
      9.81,
      11.06
    ],
    "120": [
      6.67,
      7.91,
      8.6,
      9.21,
      9.7,
      10.18,
      11.31
    ],
    "135": [
      6.05,
      7.48,
      8.22,
      8.98,
      9.86,
      10.86,
      12.41
    ],
    "150": [
      5.11,
      6.43,
      7.47,
      8.18,
      8.85,
      9.62,
      11.76
    ],
    "beat_angle": [
      42.4,
      40.9,
      38.4,
      37.7,
      37.1,
      36.4,
      36.8
    ],
    "beat_vmg": [
      4.22,
      5.12,
      5.54,
      5.72,
      5.82,
      5.96,
      5.98
    ],
    "run_angle": [
      143.5,
      143.3,
      150.3,
      157.1,
      171.5,
      156,
      144.6
    ],
    "run_vmg": [
      4.42,
      5.57,
      6.47,
      7.19,
      7.77,
      8.36,
      10.18
    ]
  }
}