{
  "sailnumber": "GRE/GRE1724",
  "country": "GRE",
  "name": "EIRINIKOS",
  "owner": "-",
  "rating": {
    "gph": 740.0,
    "osn": 711.7,
    "triple_offshore": [
      0.7445,
      1.0507,
      1.2487
    ],
    "triple_inshore": [
      0.5675,
      0.8319,
      1.0291
    ]
  },
  "boat": {
    "builder": "JEANNEAU",
    "type": "SUN ODYSSEY 37.1",
    "designer": "J.FAUROUX",
    "year": 1994,
    "sizes": {
      "loa": 11.23,
      "beam": 3.83,
      "draft": 1.85,
      "displacement": 6000.0,
      "genoa": 38.21,
      "main": 26.65,
      "spinnaker": 0.0,
      "spinnaker_asym": 0.0,
      "crew": 580.0,
      "wetted_surface": 29.45
    }
  },
  "vpp": {
    "angles": [
      52,
      60,
      75,
      90,
      110,
      120,
      135,
      150
    ],
    "speeds": [
      6,
      8,
      10,
      12,
      14,
      16,
      20
    ],
    "52": [
      4.3,
      5.26,
      5.99,
      6.58,
      6.93,
      7.08,
      7.13
    ],
    "60": [
      4.64,
      5.61,
      6.36,
      6.87,
      7.16,
      7.32,
      7.4
    ],
    "75": [
      4.89,
      5.89,
      6.65,
      7.1,
      7.36,
      7.56,
      7.83
    ],
    "90": [
      4.82,
      5.84,
      6.65,
      7.14,
      7.42,
      7.7,
      8.17
    ],
    "110": [
      4.39,
      5.46,
      6.35,
      6.99,
      7.36,
      7.65,
      8.25
    ],
    "120": [
      4.06,
      5.12,
      6.0,
      6.75,
      7.22,
      7.53,
      8.13
    ],
    "135": [
      3.54,
      4.57,
      5.44,
      6.22,
      6.86,
      7.27,
      7.85
    ],
    "150": [
      3.06,
      4.02,
      4.89,
      5.65,
      6.35,
      6.92,
      7.58
    ],
    "beat_angle": [
      46.5,
      44.7,
      43.5,
      43,
      42.2,
      41.7,
      41.9
    ],
    "beat_vmg": [
      2.72,
      3.39,
      3.9,
      4.33,
      4.66,
      4.79,
      4.8
    ],
    "run_angle": [
      158.9,
      162.7,
      167.4,
      170.7,
      171.9,
      173.4,
      178.7
    ],
    "run_vmg": [
      2.66,
      3.52,
      4.33,
      5.06,
      5.73,
      6.36,
      7.25
    ]
  }
}