{
  "sailnumber": "GRE/GRE517",
  "country": "GRE",
  "name": "ALLEGORIA",
  "owner": "-",
  "rating": {
    "gph": 623.6,
    "osn": 605.6,
    "triple_offshore": [
      0.9448,
      1.223,
      1.3648
    ],
    "triple_inshore": [
      0.734,
      0.9956,
      1.1461
    ]
  },
  "boat": {
    "builder": "BAVARIA",
    "type": "BAVARIA 35 MATCH",
    "designer": "J & J",
    "year": 2004,
    "sizes": {
      "loa": 10.84,
      "beam": 3.28,
      "draft": 2.01,
      "displacement": 5864.0,
      "genoa": 30.27,
      "main": 40.9,
      "spinnaker": 83.94,
      "spinnaker_asym": 0.0,
      "crew": 630.0,
      "wetted_surface": 26.66
    }
  },
  "vpp": {
    "angles": [
      52,
      60,
      75,
      90,
      110,
      120,
      135,
      150
    ],
    "speeds": [
      6,
      8,
      10,
      12,
      14,
      16,
      20
    ],
    "52": [
      5.23,
      6.23,
      6.88,
      7.17,
      7.28,
      7.33,
      7.41
    ],
    "60": [
      5.51,
      6.52,
      7.09,
      7.35,
      7.48,
      7.53,
      7.6
    ],
    "75": [
      5.73,
      6.73,
      7.24,
      7.51,
      7.71,
      7.86,
      7.98
    ],
    "90": [
      5.67,
      6.76,
      7.32,
      7.54,
      7.8,
      8.04,
      8.45
    ],
    "110": [
      5.65,
      6.83,
      7.42,
      7.78,
      8.12,
      8.35,
      8.73
    ],
    "120": [
      5.49,
      6.67,
      7.33,
      7.73,
      8.12,
      8.53,
      9.11
    ],
    "135": [
      4.97,
      6.1,
      6.98,
      7.45,
      7.82,
      8.22,
      9.16
    ],
    "150": [
      4.21,
      5.29,
      6.24,
      7.01,
      7.44,
      7.78,
      8.58
    ],
    "beat_angle": [
      42.3,
      40.8,
      40.3,
      39.4,
      38.7,
      38.5,
      38.2
    ],
    "beat_vmg": [
      3.46,
      4.17,
      4.72,
      5.01,
      5.13,
      5.18,
      5.29
    ],
    "run_angle": [
      144.8,
      149.7,
      151.5,
      156.8,
      174.6,
      180,
      180
    ],
    "run_vmg": [
      3.64,
      4.58,
      5.41,
      6.15,
      6.79,
      7.29,
      7.98
    ]
  }
}