{
  "sailnumber": "GRE/GRE523",
  "country": "GRE",
  "name": "ORCA",
  "rating": {
    "gph": 662.5,
    "osn": 645.1,
    "triple_offshore": [
      0.8139,
      1.01,
      1.1281
    ],
    "triple_inshore": [
      0.64,
      0.8258,
      0.9328
    ]
  },
  "boat": {
    "builder": "J COMPOSITES",
    "type": "J-80 OD",
    "designer": "JOHNSTONE",
    "year": 1995,
    "sizes": {
      "loa": 8.032,
      "beam": 2.49,
      "draft": 1.5,
      "displacement": 1437.0,
      "genoa": 13.98,
      "main": 21.53,
      "spinnaker": 0.0,
      "spinnaker_asym": 64.99,
      "crew": 350.0,
      "wetted_surface": 13.22
    },
    "stability_index": 106.8
  },
  "vpp": {
    "angles": [
      52,
      60,
      75,
      90,
      110,
      120,
      135,
      150
    ],
    "speeds": [
      6,
      8,
      10,
      12,
      14,
      16,
      20
    ],
    "52": [
      5.01,
      5.83,
      6.22,
      6.36,
      6.44,
      6.48,
      6.49
    ],
    "60": [
      5.25,
      6.01,
      6.37,
      6.55,
      6.64,
      6.7,
      6.75
    ],
    "75": [
      5.39,
      6.12,
      6.51,
      6.78,
      6.96,
      7.08,
      7.21
    ],
    "90": [
      5.48,
      6.23,
      6.52,
      6.88,
      7.18,
      7.43,
      7.76
    ],
    "110": [
      5.61,
      6.44,
      6.9,
      7.21,
      7.5,
      7.78,
      8.33
    ],
    "120": [
      5.49,
      6.4,
      6.96,
      7.44,
      7.88,
      8.28,
      9.17
    ],
    "135": [
      4.97,
      6.04,
      6.71,
      7.31,
      7.96,
      8.77,
      11.05
    ],
    "150": [
      4.24,
      5.32,
      6.11,
      6.66,
      7.11,
      7.67,
      10.18
    ],
    "beat_angle": [
      42.6,
      40.5,
      38.2,
      37.8,
      37.8,
      37.8,
      39
    ],
    "beat_vmg": [
      3.31,
      4.0,
      4.41,
      4.54,
      4.6,
      4.62,
      4.57
    ],
    "run_angle": [
      144.8,
      148.7,
      149.6,
      149.6,
      147.3,
      144.3,
      142.2
    ],
    "run_vmg": [
      3.67,
      4.6,
      5.29,
      5.77,
      6.16,
      6.64,
      8.81
    ]
  }
}