{
  "rating": {
    "triple_offshore": [
      0.9867, 
      1.2455, 
      1.3831
    ], 
    "triple_inshore": [
      0.7622, 
      1.0135, 
      1.1535
    ], 
    "gph": 607.8, 
    "osn": 593.7
  }, 
  "sailnumber": "GRE/GRE75", 
  "name": "EST EMAR", 
  "country": "GRE", 
  "owner": "-", 
  "boat": {
    "builder": "X-YACHTS", 
    "designer": "JEPPESEN", 
    "type": "X-35 OD", 
    "sizes": {
      "beam": 3.25, 
      "spinnaker": 96.12, 
      "loa": 10.6, 
      "draft": 2.17, 
      "wetted_surface": 24.38, 
      "main": 42.84, 
      "genoa": 34.07, 
      "displacement": 4479.0, 
      "spinnaker_asym": 87.33, 
      "crew": 420.0
    }, 
    "year": 2005
  }, 
  "vpp": {
    "beat_vmg": [
      3.6, 
      4.34, 
      4.81, 
      5.01, 
      5.11, 
      5.21, 
      5.23
    ], 
    "150": [
      4.37, 
      5.47, 
      6.45, 
      7.13, 
      7.55, 
      7.99, 
      9.03
    ], 
    "135": [
      5.19, 
      6.38, 
      7.13, 
      7.58, 
      8.05, 
      8.59, 
      9.96
    ], 
    "75": [
      6.15, 
      7.0, 
      7.4, 
      7.66, 
      7.8, 
      7.89, 
      8.04
    ], 
    "run_angle": [
      141.4, 
      148.5, 
      151.1, 
      159, 
      180, 
      180, 
      180
    ], 
    "110": [
      5.97, 
      7.03, 
      7.54, 
      7.93, 
      8.17, 
      8.45, 
      8.93
    ], 
    "52": [
      5.5, 
      6.53, 
      7.0, 
      7.15, 
      7.22, 
      7.29, 
      7.38
    ], 
    "beat_angle": [
      42.8, 
      42.1, 
      40.5, 
      39.1, 
      38.8, 
      38.4, 
      38.9
    ], 
    "angles": [
      52, 
      60, 
      75, 
      90, 
      110, 
      120, 
      135, 
      150
    ], 
    "120": [
      5.76, 
      6.89, 
      7.44, 
      7.93, 
      8.41, 
      8.74, 
      9.28
    ], 
    "90": [
      6.14, 
      7.04, 
      7.42, 
      7.77, 
      8.1, 
      8.34, 
      8.51
    ], 
    "60": [
      5.84, 
      6.81, 
      7.21, 
      7.36, 
      7.44, 
      7.48, 
      7.63
    ], 
    "speeds": [
      6, 
      8, 
      10, 
      12, 
      14, 
      16, 
      20
    ], 
    "run_vmg": [
      3.78, 
      4.74, 
      5.6, 
      6.31, 
      6.93, 
      7.39, 
      8.23
    ]
  }
}