{
  "sailnumber": "GRE/GRE931",
  "country": "GRE",
  "name": "ROSA F",
  "rating": {
    "gph": 751.2,
    "osn": 723.5,
    "triple_offshore": [
      0.6811,
      0.9101,
      1.0309
    ],
    "triple_inshore": [
      0.5304,
      0.7372,
      0.8654
    ]
  },
  "boat": {
    "builder": "OLYMPIC MARINE",
    "type": "CARTER 33",
    "designer": "R.CARTER",
    "year": 1971,
    "sizes": {
      "loa": 9.961,
      "beam": 3.33,
      "draft": 1.81,
      "displacement": 4992.0,
      "genoa": 27.93,
      "main": 20.65,
      "spinnaker": 68.13,
      "spinnaker_asym": 0.0,
      "crew": 450.0,
      "wetted_surface": 21.96
    },
    "stability_index": -1.0
  },
  "vpp": {
    "angles": [
      52,
      60,
      75,
      90,
      110,
      120,
      135,
      150
    ],
    "speeds": [
      6,
      8,
      10,
      12,
      14,
      16,
      20,
      24
    ],
    "52": [
      4.16,
      5.0,
      5.58,
      5.96,
      6.18,
      6.3,
      6.38,
      6.33
    ],
    "60": [
      4.38,
      5.22,
      5.8,
      6.15,
      6.36,
      6.49,
      6.6,
      6.59
    ],
    "75": [
      4.51,
      5.37,
      5.98,
      6.33,
      6.55,
      6.71,
      6.92,
      6.98
    ],
    "90": [
      4.55,
      5.51,
      6.14,
      6.46,
      6.63,
      6.79,
      7.1,
      7.3
    ],
    "110": [
      4.66,
      5.67,
      6.32,
      6.68,
      6.95,
      7.17,
      7.43,
      7.61
    ],
    "120": [
      4.52,
      5.54,
      6.25,
      6.66,
      6.95,
      7.21,
      7.67,
      7.95
    ],
    "135": [
      4.06,
      5.09,
      5.92,
      6.44,
      6.78,
      7.08,
      7.63,
      8.2
    ],
    "150": [
      3.49,
      4.48,
      5.33,
      6.02,
      6.46,
      6.78,
      7.33,
      7.88
    ],
    "beat_angle": [
      44.2,
      42.2,
      40.6,
      40,
      40,
      40,
      39.9,
      41
    ],
    "beat_vmg": [
      2.71,
      3.34,
      3.79,
      4.09,
      4.28,
      4.38,
      4.43,
      4.32
    ],
    "run_angle": [
      146.9,
      150.3,
      152.9,
      157.2,
      169.6,
      177.2,
      179,
      179
    ],
    "run_vmg": [
      3.02,
      3.88,
      4.62,
      5.28,
      5.85,
      6.31,
      6.91,
      7.42
    ]
  }
}