{
  "sailnumber": "ITA/FRA42042",
  "country": "ITA",
  "name": "SUSPIRIA THE REVENGE",
  "rating": {
    "gph": 538.3,
    "osn": 524.2,
    "triple_offshore": [
      0.9986,
      1.2469,
      1.3757
    ],
    "triple_inshore": [
      0.7815,
      1.0189,
      1.1361
    ]
  },
  "boat": {
    "builder": "Nautor",
    "type": "Swan  42",
    "designer": "Swan NY/Club Frers",
    "year": 2006,
    "sizes": {
      "loa": 12.96,
      "beam": 3.91,
      "draft": 2.74,
      "displacement": 7744.0,
      "genoa": 47.27,
      "main": 61.54,
      "spinnaker": 0.0,
      "spinnaker_asym": 185.5,
      "crew": 820.0,
      "wetted_surface": 34.83
    },
    "stability_index": 137.0
  },
  "vpp": {
    "angles": [
      52,
      60,
      75,
      90,
      110,
      120,
      135,
      150
    ],
    "speeds": [
      6,
      8,
      10,
      12,
      14,
      16,
      20
    ],
    "52": [
      6.3,
      7.35,
      7.82,
      8.02,
      8.13,
      8.2,
      8.27
    ],
    "60": [
      6.61,
      7.58,
      8.02,
      8.24,
      8.36,
      8.45,
      8.54
    ],
    "75": [
      6.82,
      7.72,
      8.18,
      8.48,
      8.7,
      8.84,
      9.03
    ],
    "90": [
      6.69,
      7.66,
      8.18,
      8.55,
      8.88,
      9.16,
      9.55
    ],
    "110": [
      6.72,
      7.86,
      8.44,
      8.79,
      9.08,
      9.35,
      9.87
    ],
    "120": [
      6.57,
      7.8,
      8.44,
      8.96,
      9.4,
      9.77,
      10.5
    ],
    "135": [
      5.92,
      7.32,
      8.14,
      8.73,
      9.33,
      10.0,
      11.68
    ],
    "150": [
      5.0,
      6.29,
      7.37,
      8.1,
      8.57,
      9.02,
      10.36
    ],
    "beat_angle": [
      42.4,
      40,
      38.4,
      37.5,
      37,
      37.2,
      37.6
    ],
    "beat_vmg": [
      4.18,
      5.03,
      5.5,
      5.71,
      5.82,
      5.89,
      5.92
    ],
    "run_angle": [
      143,
      146,
      149.6,
      151.4,
      150.2,
      147.9,
      143.9
    ],
    "run_vmg": [
      4.33,
      5.45,
      6.38,
      7.03,
      7.42,
      7.82,
      8.97
    ]
  }
}