{
  "rating": {
    "triple_offshore": [
      0.9283, 
      1.2294, 
      1.3931
    ], 
    "triple_inshore": [
      0.7107, 
      0.9794, 
      1.1455
    ], 
    "gph": 623.6, 
    "osn": 606.0
  }, 
  "sailnumber": "ITA/ITAANNAC", 
  "name": "ANNA", 
  "country": "ITA", 
  "owner": "-", 
  "boat": {
    "builder": "JEANNEAU", 
    "designer": "BRIAND", 
    "type": "SUN ODYSSEY 409", 
    "sizes": {
      "beam": 3.99, 
      "spinnaker": 0.0, 
      "loa": 11.98, 
      "draft": 2.09, 
      "wetted_surface": 31.9, 
      "main": 36.68, 
      "genoa": 47.27, 
      "displacement": 7707.0, 
      "spinnaker_asym": 134.73, 
      "crew": 455.0
    }, 
    "year": 2011
  }, 
  "vpp": {
    "beat_vmg": [
      3.25, 
      3.95, 
      4.49, 
      4.94, 
      5.2, 
      5.35, 
      5.46
    ], 
    "150": [
      4.19, 
      5.27, 
      6.3, 
      7.09, 
      7.51, 
      7.81, 
      8.38
    ], 
    "135": [
      4.95, 
      6.19, 
      7.19, 
      7.71, 
      8.08, 
      8.49, 
      9.39
    ], 
    "75": [
      5.72, 
      6.77, 
      7.39, 
      7.72, 
      7.98, 
      8.2, 
      8.48
    ], 
    "run_angle": [
      144.6, 
      147.5, 
      146.1, 
      148.6, 
      150.4, 
      174.8, 
      177.8
    ], 
    "110": [
      5.76, 
      7.0, 
      7.67, 
      8.07, 
      8.45, 
      8.69, 
      9.08
    ], 
    "52": [
      5.05, 
      6.03, 
      6.83, 
      7.31, 
      7.54, 
      7.65, 
      7.74
    ], 
    "beat_angle": [
      44.3, 
      42.7, 
      42.7, 
      41.9, 
      40.6, 
      40, 
      39.4
    ], 
    "angles": [
      52, 
      60, 
      75, 
      90, 
      110, 
      120, 
      135, 
      150
    ], 
    "120": [
      5.58, 
      6.83, 
      7.56, 
      7.98, 
      8.4, 
      8.85, 
      9.49
    ], 
    "90": [
      5.72, 
      6.88, 
      7.58, 
      7.85, 
      8.02, 
      8.28, 
      8.8
    ], 
    "60": [
      5.4, 
      6.42, 
      7.15, 
      7.53, 
      7.76, 
      7.88, 
      7.99
    ], 
    "speeds": [
      6, 
      8, 
      10, 
      12, 
      14, 
      16, 
      20
    ], 
    "run_vmg": [
      3.62, 
      4.57, 
      5.46, 
      6.14, 
      6.51, 
      6.97, 
      7.77
    ]
  }
}