{
  "sailnumber": "ESP/ESP5601_C",
  "country": "ESP",
  "name": "ELMAR I",
  "owner": "-",
  "rating": {
    "gph": 670.6,
    "osn": 650.1,
    "triple_offshore": [
      0.8452,
      1.151,
      1.327
    ],
    "triple_inshore": [
      0.6403,
      0.9126,
      1.0947
    ]
  },
  "boat": {
    "builder": "JEANNEAU",
    "type": "SUN ODYSSEY 42.2 ",
    "designer": "DUMAS",
    "year": 1991,
    "sizes": {
      "loa": 12.28,
      "beam": 3.98,
      "draft": 1.83,
      "displacement": 7177.0,
      "genoa": 52.67,
      "main": 34.6,
      "spinnaker": 0.0,
      "spinnaker_asym": 0.0,
      "crew": 670.0,
      "wetted_surface": 31.51
    }
  },
  "vpp": {
    "angles": [
      52,
      60,
      75,
      90,
      110,
      120,
      135,
      150
    ],
    "speeds": [
      6,
      8,
      10,
      12,
      14,
      16,
      20
    ],
    "52": [
      4.92,
      5.91,
      6.69,
      7.15,
      7.35,
      7.43,
      7.47
    ],
    "60": [
      5.3,
      6.31,
      7.02,
      7.39,
      7.59,
      7.69,
      7.75
    ],
    "75": [
      5.63,
      6.65,
      7.26,
      7.59,
      7.83,
      8.03,
      8.24
    ],
    "90": [
      5.59,
      6.65,
      7.3,
      7.65,
      7.92,
      8.19,
      8.63
    ],
    "110": [
      4.99,
      6.15,
      7.06,
      7.53,
      7.86,
      8.19,
      8.85
    ],
    "120": [
      4.74,
      5.8,
      6.72,
      7.34,
      7.71,
      8.04,
      8.72
    ],
    "135": [
      4.07,
      5.14,
      6.06,
      6.86,
      7.39,
      7.74,
      8.4
    ],
    "150": [
      3.45,
      4.48,
      5.38,
      6.19,
      6.9,
      7.4,
      8.05
    ],
    "beat_angle": [
      45.2,
      44,
      43.9,
      42.7,
      42.4,
      42.1,
      42.8
    ],
    "beat_vmg": [
      3.14,
      3.82,
      4.37,
      4.78,
      4.97,
      5.06,
      5.05
    ],
    "run_angle": [
      150.1,
      156.9,
      164.7,
      169.4,
      171.1,
      174.6,
      178.9
    ],
    "run_vmg": [
      2.98,
      3.9,
      4.73,
      5.5,
      6.21,
      6.86,
      7.68
    ]
  }
}