{
  "sailnumber": "USA/USA52090",
  "country": "USA",
  "name": "RELENTLESS",
  "rating": {
    "gph": 573.0,
    "osn": 556.5,
    "triple_offshore": [
      0.9182,
      1.1809,
      1.3162
    ],
    "triple_inshore": [
      0.7118,
      0.9587,
      1.0854
    ]
  },
  "boat": {
    "builder": "Fairport Marine",
    "type": "C&C 121",
    "designer": "Tim Jacket",
    "year": 2003,
    "sizes": {
      "loa": 12.268,
      "beam": 4.01,
      "draft": 1.99,
      "displacement": 7623.0,
      "genoa": 61.82,
      "main": 46.74,
      "spinnaker": 0.0,
      "spinnaker_asym": 152.99,
      "crew": 1080.0,
      "wetted_surface": 34.87
    },
    "stability_index": 116.8
  },
  "vpp": {
    "angles": [
      52,
      60,
      75,
      90,
      110,
      120,
      135,
      150
    ],
    "speeds": [
      6,
      8,
      10,
      12,
      14,
      16,
      20
    ],
    "52": [
      5.86,
      6.91,
      7.5,
      7.79,
      7.92,
      8.01,
      8.1
    ],
    "60": [
      6.19,
      7.16,
      7.66,
      7.95,
      8.12,
      8.23,
      8.34
    ],
    "75": [
      6.4,
      7.3,
      7.78,
      8.1,
      8.36,
      8.55,
      8.77
    ],
    "90": [
      6.34,
      7.38,
      7.94,
      8.32,
      8.61,
      8.82,
      9.16
    ],
    "110": [
      6.14,
      7.29,
      7.95,
      8.41,
      8.8,
      9.16,
      9.96
    ],
    "120": [
      5.93,
      7.16,
      7.87,
      8.38,
      8.86,
      9.3,
      10.26
    ],
    "135": [
      5.31,
      6.63,
      7.52,
      8.07,
      8.56,
      9.06,
      10.23
    ],
    "150": [
      4.5,
      5.7,
      6.73,
      7.47,
      7.89,
      8.22,
      8.9
    ],
    "beat_angle": [
      43.8,
      42,
      40,
      38.4,
      37.6,
      37.2,
      37
    ],
    "beat_vmg": [
      3.83,
      4.63,
      5.23,
      5.55,
      5.71,
      5.8,
      5.88
    ],
    "run_angle": [
      143.4,
      147.3,
      148,
      149.8,
      150.5,
      172.1,
      175.7
    ],
    "run_vmg": [
      3.9,
      4.93,
      5.83,
      6.47,
      6.83,
      7.26,
      8.07
    ]
  }
}