{"rating": {"triple_offshore": [1.0575, 1.3346, 1.54], "gph": 564.9, "triple_inshore": [0.8144, 1.0662, 1.2504]}, "sailnumber": "NOR30012", "name": "No 28 Pizza Pub", "owner": "Bjorn Erik Bjornsen", "boat": {"builder": "Carroll Marine", "designer": "Mills", "type": "C&C 30", "sizes": {"beam": 2.98, "spinnaker": 0.0, "loa": 9.15, "draft": 2.26, "main": 37.6, "genoa": 23.0, "displacement": 1922.0, "spinnaker_asym": 120.0}, "year": "2013"}, "vpp": {"beat_vmg": [3.84, 4.68, 5.08, 5.29, 5.41, 5.44, 5.47], "150": [4.64, 5.83, 6.77, 7.52, 8.28, 9.39, 12.3], "135": [5.64, 6.95, 7.72, 8.67, 9.9, 11.07, 12.63], "75": [6.56, 7.27, 7.92, 8.33, 8.57, 8.73, 9.04], "run_angle": [137.1, 143.8, 147.9, 156.3, 143.1, 138.1, 144.1], "110": [6.72, 7.54, 8.16, 8.81, 9.37, 9.85, 11.41], "52": [5.88, 6.89, 7.21, 7.38, 7.5, 7.61, 7.73], "beat_angle": [42.8, 41.3, 38.3, 37.2, 36.3, 36.4, 36.8], "angles": [52, 60, 75, 90, 110, 120, 135, 150], "120": [6.48, 7.48, 8.54, 9.19, 9.69, 10.25, 11.59], "90": [6.67, 7.28, 7.85, 8.67, 9.26, 9.57, 9.9], "60": [6.26, 7.11, 7.47, 7.71, 7.87, 8.0, 8.19], "speeds": [6, 8, 10, 12, 14, 16, 20], "run_vmg": [4.02, 5.05, 5.86, 6.56, 7.17, 8.13, 10.65]}}