{
  "sailnumber": "FRA/FRA16919",
  "country": "FRA",
  "name": "JADE",
  "owner": "-",
  "rating": {
    "gph": 673.9,
    "osn": 654.8,
    "triple_offshore": [
      0.7731,
      1.0075,
      1.1299
    ],
    "triple_inshore": [
      0.5944,
      0.8159,
      0.9362
    ]
  },
  "boat": {
    "builder": "BENETEAU SA",
    "type": "FIRST 310 GTE",
    "designer": "FINOT Jean Marie",
    "year": 1990,
    "sizes": {
      "loa": 9.147,
      "beam": 3.22,
      "draft": 1.83,
      "displacement": 3325.0,
      "genoa": 24.73,
      "main": 26.76,
      "spinnaker": 54.35,
      "spinnaker_asym": 46.43,
      "crew": 565.0,
      "wetted_surface": 21.27
    },
    "stability_index": 105.3
  },
  "vpp": {
    "angles": [
      52,
      60,
      75,
      90,
      110,
      120,
      135,
      150
    ],
    "speeds": [
      6,
      8,
      10,
      12,
      14,
      16,
      20
    ],
    "52": [
      4.87,
      5.77,
      6.36,
      6.64,
      6.74,
      6.78,
      6.76
    ],
    "60": [
      5.17,
      6.07,
      6.56,
      6.81,
      6.94,
      6.99,
      7.0
    ],
    "75": [
      5.4,
      6.29,
      6.74,
      6.99,
      7.2,
      7.36,
      7.46
    ],
    "90": [
      5.53,
      6.47,
      6.92,
      7.25,
      7.55,
      7.74,
      8.01
    ],
    "110": [
      5.29,
      6.31,
      6.84,
      7.23,
      7.65,
      8.06,
      8.8
    ],
    "120": [
      5.0,
      6.09,
      6.74,
      7.14,
      7.56,
      8.01,
      8.96
    ],
    "135": [
      4.49,
      5.54,
      6.38,
      6.86,
      7.23,
      7.66,
      8.65
    ],
    "150": [
      3.8,
      4.83,
      5.72,
      6.44,
      6.87,
      7.22,
      8.04
    ],
    "beat_angle": [
      43.1,
      42.4,
      41.2,
      39.4,
      39,
      39,
      39.8
    ],
    "beat_vmg": [
      3.15,
      3.81,
      4.33,
      4.65,
      4.75,
      4.77,
      4.72
    ],
    "run_angle": [
      146.5,
      151,
      153,
      159,
      180,
      180,
      180
    ],
    "run_vmg": [
      3.29,
      4.19,
      4.97,
      5.67,
      6.31,
      6.76,
      7.46
    ]
  }
}