{
  "sailnumber": "FRA/FRA43856",
  "country": "FRA",
  "name": "WHITE PEARL",
  "rating": {
    "gph": 597.0,
    "osn": 578.4,
    "triple_offshore": [
      0.8644,
      1.1416,
      1.2862
    ],
    "triple_inshore": [
      0.6665,
      0.9213,
      1.074
    ]
  },
  "boat": {
    "builder": "X-YACHT",
    "type": "X 43 Std",
    "designer": "JEPPESEN Nielsen",
    "year": 2003,
    "sizes": {
      "loa": 12.913,
      "beam": 3.95,
      "draft": 2.19,
      "displacement": 8819.0,
      "genoa": 41.47,
      "main": 50.14,
      "spinnaker": 117.71,
      "spinnaker_asym": 0.0,
      "crew": 851.0,
      "wetted_surface": 35.35
    },
    "stability_index": 119.7
  },
  "vpp": {
    "angles": [
      52,
      60,
      75,
      90,
      110,
      120,
      135,
      150
    ],
    "speeds": [
      6,
      8,
      10,
      12,
      14,
      16,
      20
    ],
    "52": [
      5.37,
      6.42,
      7.2,
      7.6,
      7.75,
      7.83,
      7.91
    ],
    "60": [
      5.71,
      6.76,
      7.46,
      7.81,
      7.98,
      8.06,
      8.11
    ],
    "75": [
      5.99,
      7.04,
      7.65,
      7.99,
      8.22,
      8.39,
      8.55
    ],
    "90": [
      5.9,
      7.01,
      7.74,
      8.02,
      8.29,
      8.56,
      9.02
    ],
    "110": [
      5.87,
      7.16,
      7.88,
      8.29,
      8.64,
      8.88,
      9.3
    ],
    "120": [
      5.71,
      6.99,
      7.79,
      8.23,
      8.65,
      9.08,
      9.72
    ],
    "135": [
      5.14,
      6.37,
      7.37,
      7.95,
      8.35,
      8.78,
      9.78
    ],
    "150": [
      4.33,
      5.49,
      6.51,
      7.39,
      7.92,
      8.31,
      9.16
    ],
    "beat_angle": [
      43.8,
      41.8,
      41.4,
      40.6,
      39.6,
      39.4,
      38.8
    ],
    "beat_vmg": [
      3.48,
      4.25,
      4.85,
      5.24,
      5.4,
      5.47,
      5.6
    ],
    "run_angle": [
      143.9,
      148.4,
      150.5,
      154.7,
      162.8,
      175.4,
      178.4
    ],
    "run_vmg": [
      3.75,
      4.75,
      5.64,
      6.45,
      7.1,
      7.67,
      8.44
    ]
  }
}