{
  "rating": {
    "triple_offshore": [
      0.8795, 
      1.1152, 
      1.2596
    ], 
    "triple_inshore": [
      0.6833, 
      0.9177, 
      1.0458
    ], 
    "gph": 678.3, 
    "osn": 659.7
  }, 
  "sailnumber": "GER/FCA266", 
  "name": "NEXT GENERATION", 
  "country": "GER", 
  "owner": "-", 
  "boat": {
    "builder": "BENETEAU", 
    "designer": "FINOT", 
    "type": "FIRST CLASS 8", 
    "sizes": {
      "beam": 2.5, 
      "spinnaker": 44.2, 
      "loa": 7.79, 
      "draft": 1.84, 
      "wetted_surface": 14.08, 
      "main": 21.86, 
      "genoa": 18.64, 
      "displacement": 1518.0, 
      "spinnaker_asym": 0.0, 
      "crew": 411.0
    }, 
    "year": 1986
  }, 
  "vpp": {
    "beat_vmg": [
      3.3, 
      3.95, 
      4.42, 
      4.62, 
      4.72, 
      4.77, 
      4.79
    ], 
    "150": [
      3.82, 
      4.83, 
      5.68, 
      6.24, 
      6.63, 
      7.08, 
      8.17
    ], 
    "135": [
      4.59, 
      5.57, 
      6.2, 
      6.61, 
      7.1, 
      7.64, 
      9.21
    ], 
    "75": [
      5.48, 
      6.12, 
      6.48, 
      6.85, 
      7.11, 
      7.24, 
      7.36
    ], 
    "run_angle": [
      146.7, 
      151.1, 
      153.4, 
      170.5, 
      180, 
      180, 
      180
    ], 
    "110": [
      5.28, 
      6.13, 
      6.59, 
      7.12, 
      7.64, 
      7.95, 
      8.57
    ], 
    "52": [
      4.98, 
      5.81, 
      6.2, 
      6.36, 
      6.45, 
      6.51, 
      6.58
    ], 
    "beat_angle": [
      41.9, 
      40.8, 
      38.3, 
      36.8, 
      35.9, 
      35.6, 
      35.8
    ], 
    "angles": [
      52, 
      60, 
      75, 
      90, 
      110, 
      120, 
      135, 
      150
    ], 
    "120": [
      5.1, 
      6.02, 
      6.48, 
      6.97, 
      7.53, 
      8.21, 
      9.21
    ], 
    "90": [
      5.47, 
      6.13, 
      6.57, 
      6.88, 
      7.28, 
      7.65, 
      7.98
    ], 
    "60": [
      5.25, 
      5.99, 
      6.34, 
      6.57, 
      6.69, 
      6.76, 
      6.86
    ], 
    "speeds": [
      6, 
      8, 
      10, 
      12, 
      14, 
      16, 
      20
    ], 
    "run_vmg": [
      3.31, 
      4.18, 
      4.95, 
      5.64, 
      6.16, 
      6.53, 
      7.39
    ]
  }
}