{
  "rating": {
    "triple_offshore": [
      0.9539, 
      1.2535, 
      1.4198
    ], 
    "gph": 610.2, 
    "triple_inshore": [
      0.7329, 
      1.0107, 
      1.1882
    ]
  }, 
  "sailnumber": "GER7142", 
  "name": "CONCETTA", 
  "country": "GER", 
  "owner": "STEFAN HEITMANN", 
  "boat": {
    "builder": "HANSE", 
    "designer": "JUDEL/VROLIJK", 
    "type": "DEHLER 38 C", 
    "sizes": {
      "beam": 3.76, 
      "spinnaker": 101.1, 
      "loa": 11.3, 
      "draft": 2.2, 
      "main": 48.9, 
      "genoa": 35.7, 
      "displacement": 7216.0, 
      "spinnaker_asym": 0.0
    }, 
    "year": "2012"
  }, 
  "vpp": {
    "beat_vmg": [
      3.39, 
      4.11, 
      4.7, 
      5.12, 
      5.32, 
      5.43, 
      5.55
    ], 
    "150": [
      4.26, 
      5.38, 
      6.35, 
      7.16, 
      7.65, 
      8.0, 
      8.8
    ], 
    "135": [
      5.06, 
      6.21, 
      7.14, 
      7.66, 
      8.04, 
      8.45, 
      9.39
    ], 
    "75": [
      5.94, 
      6.98, 
      7.54, 
      7.86, 
      8.12, 
      8.31, 
      8.46
    ], 
    "run_angle": [
      144.6, 
      149.4, 
      151.6, 
      156.1, 
      173.2, 
      180.0, 
      180.0
    ], 
    "110": [
      5.79, 
      7.01, 
      7.65, 
      8.06, 
      8.41, 
      8.62, 
      9.02
    ], 
    "52": [
      5.25, 
      6.27, 
      7.06, 
      7.46, 
      7.61, 
      7.69, 
      7.78
    ], 
    "beat_angle": [
      43.9, 
      42.4, 
      42.2, 
      40.7, 
      39.3, 
      39.1, 
      38.7
    ], 
    "angles": [
      52, 
      60, 
      75, 
      90, 
      110, 
      120, 
      135, 
      150
    ], 
    "120": [
      5.61, 
      6.82, 
      7.54, 
      7.96, 
      8.37, 
      8.83, 
      9.38
    ], 
    "90": [
      5.92, 
      6.98, 
      7.6, 
      7.84, 
      8.12, 
      8.43, 
      8.93
    ], 
    "60": [
      5.6, 
      6.66, 
      7.34, 
      7.67, 
      7.84, 
      7.92, 
      7.99
    ], 
    "speeds": [
      6, 
      8, 
      10, 
      12, 
      14, 
      16, 
      20
    ], 
    "run_vmg": [
      3.69, 
      4.66, 
      5.5, 
      6.26, 
      6.93, 
      7.48, 
      8.2
    ]
  }
}