{
  "rating": {
    "triple_offshore": [
      1.2182, 
      1.5665, 
      1.7849
    ], 
    "triple_inshore": [
      0.9341, 
      1.2619, 
      1.4637
    ], 
    "gph": 485.1, 
    "osn": 472.3
  }, 
  "sailnumber": "GER7155", 
  "name": "JOLLY RED", 
  "country": "GER", 
  "owner": "PETER GILLEMOT", 
  "boat": {
    "builder": "CARROLL MARINE", 
    "designer": "FARR", 
    "type": "FARR 520", 
    "sizes": {
      "beam": 4.44, 
      "spinnaker": 0.0, 
      "loa": 15.839, 
      "draft": 3.28, 
      "wetted_surface": 47.6, 
      "main": 99.4, 
      "genoa": 65.0, 
      "displacement": 10904.0, 
      "spinnaker_asym": 278.0, 
      "crew": 800.0
    }, 
    "year": "2000"
  }, 
  "vpp": {
    "beat_vmg": [
      4.34, 
      5.34, 
      6.01, 
      6.36, 
      6.58, 
      6.78, 
      6.94
    ], 
    "150": [
      5.38, 
      6.77, 
      8.02, 
      8.96, 
      9.5, 
      10.14, 
      12.12
    ], 
    "135": [
      6.44, 
      8.1, 
      9.03, 
      9.71, 
      10.58, 
      11.58, 
      13.06
    ], 
    "75": [
      7.63, 
      8.8, 
      9.34, 
      9.81, 
      10.12, 
      10.34, 
      10.68
    ], 
    "run_angle": [
      141.8, 
      141.4, 
      146.6, 
      152.4, 
      151.7, 
      148.3, 
      143.2
    ], 
    "110": [
      7.48, 
      8.86, 
      9.37, 
      9.8, 
      10.27, 
      10.77, 
      12.15
    ], 
    "52": [
      6.68, 
      8.12, 
      8.76, 
      9.02, 
      9.17, 
      9.31, 
      9.58
    ], 
    "beat_angle": [
      43.4, 
      42.3, 
      40.3, 
      38.2, 
      37.4, 
      36.4, 
      35.8
    ], 
    "angles": [
      52, 
      60, 
      75, 
      90, 
      110, 
      120, 
      135, 
      150
    ], 
    "120": [
      7.21, 
      8.73, 
      9.49, 
      10.04, 
      10.52, 
      11.0, 
      12.22
    ], 
    "90": [
      7.62, 
      8.78, 
      9.35, 
      9.95, 
      10.55, 
      10.99, 
      11.46
    ], 
    "60": [
      7.15, 
      8.51, 
      9.05, 
      9.31, 
      9.5, 
      9.65, 
      10.03
    ], 
    "speeds": [
      6, 
      8, 
      10, 
      12, 
      14, 
      16, 
      20
    ], 
    "run_vmg": [
      4.66, 
      5.87, 
      6.95, 
      7.74, 
      8.22, 
      8.78, 
      10.49
    ]
  }
}