{
  "sailnumber": "GER/GER8190",
  "country": "GER",
  "name": "ADDICTIF",
  "rating": {
    "gph": 605.4,
    "osn": 589.3,
    "triple_offshore": [
      0.8697,
      1.1134,
      1.2697
    ],
    "triple_inshore": [
      0.6717,
      0.8938,
      1.0165
    ]
  },
  "boat": {
    "builder": "STRUCTURES",
    "type": "POGO 30",
    "designer": "FINOT-CONQ",
    "year": 2013,
    "sizes": {
      "loa": 9.14,
      "beam": 3.71,
      "draft": 1.96,
      "displacement": 3065.0,
      "genoa": 26.42,
      "main": 34.5,
      "spinnaker": 0.0,
      "spinnaker_asym": 86.84,
      "crew": 500.0,
      "wetted_surface": 21.44
    },
    "stability_index": 120.9
  },
  "vpp": {
    "angles": [
      52,
      60,
      75,
      90,
      110,
      120,
      135,
      150
    ],
    "speeds": [
      6,
      8,
      10,
      12,
      14,
      16,
      20
    ],
    "52": [
      5.46,
      6.46,
      6.98,
      7.2,
      7.31,
      7.38,
      7.48
    ],
    "60": [
      5.82,
      6.74,
      7.19,
      7.46,
      7.65,
      7.77,
      7.92
    ],
    "75": [
      6.18,
      6.95,
      7.39,
      7.85,
      8.19,
      8.39,
      8.61
    ],
    "90": [
      6.19,
      7.01,
      7.54,
      8.12,
      8.55,
      8.89,
      9.39
    ],
    "110": [
      5.92,
      6.91,
      7.51,
      8.2,
      8.89,
      9.58,
      10.88
    ],
    "120": [
      5.67,
      6.8,
      7.41,
      8.07,
      8.87,
      9.76,
      11.13
    ],
    "135": [
      5.1,
      6.32,
      7.09,
      7.64,
      8.29,
      9.09,
      11.1
    ],
    "150": [
      4.33,
      5.47,
      6.42,
      7.05,
      7.45,
      7.89,
      9.4
    ],
    "beat_angle": [
      44.2,
      42.3,
      40.5,
      39,
      38.1,
      37.8,
      37.6
    ],
    "beat_vmg": [
      3.55,
      4.3,
      4.82,
      5.08,
      5.22,
      5.28,
      5.34
    ],
    "run_angle": [
      144.3,
      147.9,
      148.9,
      150.7,
      148.4,
      174.8,
      142.6
    ],
    "run_vmg": [
      3.75,
      4.73,
      5.56,
      6.11,
      6.45,
      6.96,
      8.14
    ]
  }
}